skyfire_sdk/__init__.py
skyfire_sdk/api_client.py
skyfire_sdk/api_response.py
skyfire_sdk/configuration.py
skyfire_sdk/exceptions.py
skyfire_sdk/py.typed
skyfire_sdk/rest.py
skyfire_sdk/api/__init__.py
skyfire_sdk/api/api_ninja_api.py
skyfire_sdk/api/chat_api.py
skyfire_sdk/api/email_api.py
skyfire_sdk/api/financial_datasets_ai_api.py
skyfire_sdk/api/gift_card_api.py
skyfire_sdk/api/net_nut_api.py
skyfire_sdk/api/open_ai_api.py
skyfire_sdk/api/open_router_api.py
skyfire_sdk/api/organization_api.py
skyfire_sdk/api/payments_api.py
skyfire_sdk/api/perplexity_api.py
skyfire_sdk/api/pricing_culture_api.py
skyfire_sdk/api/toolkit_api.py
skyfire_sdk/api/venice_api.py
skyfire_sdk/api/vetric_api.py
skyfire_sdk/api/wallet_management_api.py
skyfire_sdk/models/__init__.py
skyfire_sdk/models/api_ninja_crypto_price_response.py
skyfire_sdk/models/api_ninja_dns_lookup_response.py
skyfire_sdk/models/api_ninja_dns_record.py
skyfire_sdk/models/api_ninja_ip_lookup_response.py
skyfire_sdk/models/api_ninja_stock_response.py
skyfire_sdk/models/api_ninja_weather_response.py
skyfire_sdk/models/balance_sheet.py
skyfire_sdk/models/balance_sheets200_response.py
skyfire_sdk/models/bridge_destination.py
skyfire_sdk/models/bridge_source_deposit_address.py
skyfire_sdk/models/bridge_virtual_account.py
skyfire_sdk/models/cash_flow_statement.py
skyfire_sdk/models/cash_flow_statements200_response.py
skyfire_sdk/models/chat_completion_message_tool_call.py
skyfire_sdk/models/chat_completion_message_tool_call_function.py
skyfire_sdk/models/chat_completion_request_message.py
skyfire_sdk/models/chat_completion_response_message.py
skyfire_sdk/models/chat_completion_response_message_function_call.py
skyfire_sdk/models/chat_completion_stream_options.py
skyfire_sdk/models/chat_completion_token_logprob.py
skyfire_sdk/models/chat_completion_token_logprob_top_logprobs_inner.py
skyfire_sdk/models/chat_completion_tool.py
skyfire_sdk/models/claim.py
skyfire_sdk/models/claim_group.py
skyfire_sdk-0.6.11.dist-info/METADATA
skyfire_sdk-0.6.11.dist-info/WHEEL
skyfire_sdk-0.6.11.dist-info/top_level.txt
skyfire_sdk-0.6.11.dist-info/RECORD
