Metadata-Version: 2.2
Name: skyfire-sdk
Version: 0.6.11
Summary: Skyfire SDK
Home-page: 
Author: OpenAPI Generator community
Author-email: support@skyfire.xyz
Keywords: OpenAPI,OpenAPI-Generator,Skyfire SDK
Requires-Dist: urllib3<2.1.0,>=1.25.3
Requires-Dist: python-dateutil
Requires-Dist: pydantic>=2
Requires-Dist: typing-extensions>=4.7.1
Dynamic: author
Dynamic: author-email
Dynamic: description
Dynamic: description-content-type
Dynamic: keywords
Dynamic: requires-dist
Dynamic: summary
